robloxpy/Utils.py
robloxpy/__init__.py
robloxpy/Game/External.py
robloxpy/Game/Internal.py
robloxpy/Game/__init__.py
robloxpy/Group/External.py
robloxpy/Group/Internal.py
robloxpy/Group/__init__.py
robloxpy/Market/External.py
robloxpy/Market/Internal.py
robloxpy/Market/__init__.py
robloxpy/User/External.py
robloxpy/User/Internal.py
robloxpy/User/__init__.py
robloxpy/User/Friends/External.py
robloxpy/User/Friends/Internal.py
robloxpy/User/Friends/__init__.py
robloxpy/User/Groups/External.py
robloxpy/User/Groups/Internal.py
robloxpy/User/Groups/__init__.py
robloxpy-0.2.21.dist-info/METADATA
robloxpy-0.2.21.dist-info/WHEEL
robloxpy-0.2.21.dist-info/top_level.txt
robloxpy-0.2.21.dist-info/RECORD
